wsgigo/__init__.py
wsgigo-1.3.0.dist-info/LICENSE
wsgigo-1.3.0.dist-info/METADATA
wsgigo-1.3.0.dist-info/WHEEL
wsgigo-1.3.0.dist-info/RECORD
