Metadata-Version: 2.1
Name: wsgigo
Version: 1.3.0
Summary: WSGI application router
Home-page: https://github.com/kkinder/wsgigo
License: MIT
Keywords: wsgi,router,middleware
Author: Ken Kinder
Author-email: ken+github@kkinder.com
Requires-Python: >=3.9,<4.0
Classifier: Development Status :: 4 - Beta
Classifier: Environment :: Web Environment
Classifier: Intended Audience :: Developers
Classifier: License :: OSI Approved :: MIT License
Classifier: Programming Language :: Python :: 3
Classifier: Programming Language :: Python :: 3.9
Classifier: Programming Language :: Python :: 3.10
Classifier: Programming Language :: Python :: 3.11
Classifier: Topic :: Internet :: WWW/HTTP :: WSGI
Classifier: Topic :: Software Development :: Libraries :: Python Modules
Project-URL: Repository, https://github.com/kkinder/wsgigo
